{
  "code":200,
  "data":[
    {
      "id":1,
      "hasPic":"no-pic",
      "title":"博客上线了",
      "author":"wan",
      "brief":"让您久等了，我的博客终于在这个时间段上线了!",
      "time":1488771967000,
      "category":"杂谈",
      "picPath":"",
      "commentCount":2
    },
    {
      "id":1,
      "hasPic":"",
      "title":"博客上线了",
      "author":"wan",
      "brief":"让您久等了，我的博客终于在这个时间段上线了(二)!",
      "time":1488771967000,
      "category":"杂谈",
      "picPath":"images/1.jpg",
      "commentCount":2
    },
    {
      "id":1,
      "hasPic":"",
      "title":"博客上线了",
      "author":"wan",
      "brief":"让您久等了，我的博客终于在这个时间段上线了(三)!",
      "time":1488771967000,
      "category":"杂谈",
      "picPath":"images/2.jpg",
      "commentCount":2
    },
    {
      "id":1,
      "hasPic":"",
      "title":"博客上线了",
      "author":"wan",
      "brief":"让您久等了，我的博客终于在这个时间段上线了(三)!",
      "time":1488771967000,
      "category":"杂谈",
      "picPath":"images/2.jpg",
      "commentCount":2
    }
  ],
  "error":null
}